.long-description.html
README.rst
setup.py
src/collective/__init__.py
src/collective.behavior.vat.egg-info/PKG-INFO
src/collective.behavior.vat.egg-info/SOURCES.txt
src/collective.behavior.vat.egg-info/dependency_links.txt
src/collective.behavior.vat.egg-info/entry_points.txt
src/collective.behavior.vat.egg-info/namespace_packages.txt
src/collective.behavior.vat.egg-info/not-zip-safe
src/collective.behavior.vat.egg-info/requires.txt
src/collective.behavior.vat.egg-info/top_level.txt
src/collective/behavior/__init__.py
src/collective/behavior/vat/__init__.py
src/collective/behavior/vat/behavior.py
src/collective/behavior/vat/configure.zcml
src/collective/behavior/vat/interfaces.py
src/collective/behavior/vat/schema.py
src/collective/behavior/vat/vocabulary.py
src/collective/behavior/vat/Extensions/Install.py
src/collective/behavior/vat/Extensions/__init__.py
src/collective/behavior/vat/adapter/__init__.py
src/collective/behavior/vat/adapter/configure.zcml
src/collective/behavior/vat/adapter/interface.py
src/collective/behavior/vat/docs/CREDITS.rst
src/collective/behavior/vat/docs/HISTORY.rst
src/collective/behavior/vat/docs/INSTALL.rst
src/collective/behavior/vat/docs/LICENSE.rst
src/collective/behavior/vat/locales/collective.behavior.vat.pot
src/collective/behavior/vat/locales/fi/LC_MESSAGES/collective.behavior.vat.mo
src/collective/behavior/vat/locales/fi/LC_MESSAGES/collective.behavior.vat.po
src/collective/behavior/vat/profiles/default/catalog.xml
src/collective/behavior/vat/profiles/default/metadata.xml
src/collective/behavior/vat/profiles/default/registry.xml
src/collective/behavior/vat/profiles/uninstall/registry.xml
src/collective/behavior/vat/tests/__init__.py
src/collective/behavior/vat/tests/base.py
src/collective/behavior/vat/tests/test_Adapter.py
src/collective/behavior/vat/tests/test_IVAT.py
src/collective/behavior/vat/tests/test_VAT.py
src/collective/behavior/vat/tests/test_VATRatesVocabulary.py
src/collective/behavior/vat/tests/test_functional.py
src/collective/behavior/vat/tests/test_setup.py
src/collective/behavior/vat/tests/dexterity/__init__.py
src/collective/behavior/vat/tests/dexterity/configure.zcml
src/collective/behavior/vat/tests/dexterity/folder.py
src/collective/behavior/vat/tests/dexterity/profiles/default/metadata.xml
src/collective/behavior/vat/tests/dexterity/profiles/default/registry.xml
