Metadata-Version: 1.1
Name: collective.behavior.vat
Version: 0.5
Summary: Adds VAT field to dexterity content type.
Home-page: https://github.com/collective/collective.behavior.vat/
Author: Taito Horiuchi
Author-email: taito.horiuchi@gmail.com
License: BSD
Platform: UNKNOWN
Classifier: Framework :: Plone
Classifier: Framework :: Plone :: 4.3
Classifier: License :: OSI Approved :: BSD License
Classifier: Programming Language :: Python
Classifier: Programming Language :: Python :: 2.7
